README.md
setup.py
HandLessRobot/__init__.py
HandLessRobot/robot.py
HandLessRobot.egg-info/PKG-INFO
HandLessRobot.egg-info/SOURCES.txt
HandLessRobot.egg-info/dependency_links.txt
HandLessRobot.egg-info/entry_points.txt
HandLessRobot.egg-info/not-zip-safe
HandLessRobot.egg-info/requires.txt
HandLessRobot.egg-info/top_level.txt
HandLessRobot/i18n/__init__.py
HandLessRobot/i18n/message_zh_cn.json
HandLessRobot/lib/__init__.py
HandLessRobot/lib/pipeline_plugin.py
HandLessRobot/lib/actions/__init__.py
HandLessRobot/lib/actions/appium_action.py
HandLessRobot/lib/actions/base_action.py
HandLessRobot/lib/actions/chrome_action.py
HandLessRobot/lib/actions/common_action.py
HandLessRobot/lib/actions/generate_tool.py
HandLessRobot/lib/actions/windows_action.py
HandLessRobot/lib/controls/__init__.py
HandLessRobot/lib/controls/adb_control.py
HandLessRobot/lib/controls/appium_control.py
HandLessRobot/lib/controls/minicap_control.py
HandLessRobot/lib/controls/minitouch_control.py
HandLessRobot/lib/controls/windows_control.py
HandLessRobot/lib/controls/appium_sub/__init__.py
HandLessRobot/lib/controls/appium_sub/android.py
HandLessRobot/lib/controls/appium_sub/ios.py
HandLessRobot/lib/controls/windows/__init__.py
HandLessRobot/lib/controls/windows/uia.py
HandLessRobot/lib/controls/windows/win32.py